mojangles/__init__.py
mojangles-1.0.1.dist-info/METADATA
mojangles-1.0.1.dist-info/WHEEL
mojangles-1.0.1.dist-info/licenses/LICENSE
mojangles-1.0.1.dist-info/RECORD
